gadfastopenapi/__init__.py
gadfastopenapi/const/__init__.py
gadfastopenapi/const/fastapi.py
gadfastopenapi/const/pydantic.py
gadfastopenapi/const/specification.py
gadfastopenapi/const/symbols.py
gadfastopenapi/extensions/__init__.py
gadfastopenapi/extensions/affix/__init__.py
gadfastopenapi/extensions/affix/handlers.py
gadfastopenapi/extensions/errors/__init__.py
gadfastopenapi/extensions/errors/exceptions.py
gadfastopenapi/extensions/errors/utils.py
gadfastopenapi/extensions/operationid/__init__.py
gadfastopenapi/extensions/operationid/handlers.py
gadfastopenapi/utils/__init__.py
gadfastopenapi/utils/specification.py
tests/__init__.py
tests/test_init.py
gadfastopenapi-0.0.1.dist-info/LICENSE
gadfastopenapi-0.0.1.dist-info/METADATA
gadfastopenapi-0.0.1.dist-info/WHEEL
gadfastopenapi-0.0.1.dist-info/top_level.txt
gadfastopenapi-0.0.1.dist-info/RECORD
