Metadata-Version: 2.1
Name: gadfastopenapi
Version: 0.0.1
Summary: Customize and override OpenAPI schema details in FastAPI with ease
Home-page: https://github.com/AlexDemure/gadfastopenapi
Author: Alexander Grishchenko
Author-email: alexanderdemure@gmail.com
Classifier: Programming Language :: Python :: 3
Classifier: License :: OSI Approved :: MIT License
Classifier: Operating System :: OS Independent
Requires-Python: >=3.8
License-File: LICENSE
